posit/envar_decrypter/envar_decrypter.py
posit_decrypt_envars-0.2.1.dist-info/METADATA
posit_decrypt_envars-0.2.1.dist-info/WHEEL
posit_decrypt_envars-0.2.1.dist-info/top_level.txt
posit_decrypt_envars-0.2.1.dist-info/RECORD
