Metadata-Version: 2.1
Name: posit-decrypt-envars
Version: 0.2.1
Summary: POSIT Environment Variables Decrypter
Home-page: UNKNOWN
License: Other/Proprietary License
Platform: any
Classifier: License :: Other/Proprietary License
Classifier: Natural Language :: English
Classifier: Operating System :: OS Independent
Classifier: Programming Language :: Python :: 3 :: Only
Classifier: Programming Language :: Python :: 3.7
Classifier: Programming Language :: Python :: 3.8
Classifier: Programming Language :: Python :: 3.9
Classifier: Programming Language :: Python :: 3.10
Requires-Python: <3.11,>=3.7
Requires-Dist: cryptography
